de/tpl_project.py
de_tpl_project-0.2.3.data/data/.gitignore
de_tpl_project-0.2.3.data/data/.gitlab-ci.yml
de_tpl_project-0.2.3.data/data/CONTRIBUTING.rst
de_tpl_project-0.2.3.data/data/LICENSE.md
de_tpl_project-0.2.3.data/data/README.md
de_tpl_project-0.2.3.data/data/SECURITY.md
de_tpl_project-0.2.3.data/data/requirements.txt
de_tpl_project-0.2.3.data/data/setup.py
de_tpl_project-0.2.3.data/data/test_requirements.txt
de_tpl_project-0.2.3.data/data/templates/de_otf_LICENSE.md
de_tpl_project-0.2.3.data/data/templates/de_otf_SECURITY.md
de_tpl_project-0.2.3.data/data/templates/de_otf_de_tpl_.gitignore
de_tpl_project-0.2.3.data/data/templates/de_otf_de_tpl_.gitlab-ci.yml
de_tpl_project-0.2.3.data/data/templates/de_otf_de_tpl_CONTRIBUTING.rst
de_tpl_project-0.2.3.data/data/templates/de_otf_de_tpl_dev_requirements.txt
de_tpl_project-0.2.3.data/data/templates/de_otf_setup.py
de_tpl_project-0.2.3.data/data/templates/de_tpl_README.md
de_tpl_project-0.2.3.data/data/templates/docs/de_otf_Makefile
de_tpl_project-0.2.3.data/data/templates/docs/de_otf_de_tpl_conf.py
de_tpl_project-0.2.3.data/data/templates/docs/de_otf_de_tpl_index.rst
de_tpl_project-0.2.3.data/data/templates/docs/de_otf_de_tpl_requirements.txt
de_tpl_project-0.2.3.data/data/templates/docs/features_and_examples.rst
de_tpl_project-0.2.3.data/data/templates/tests/de_otf_conftest.py
de_tpl_project-0.2.3.data/data/templates/tests/de_otf_de_tpl_requirements.txt
de_tpl_project-0.2.3.data/data/templates/tests/de_otf_de_tpl_test_{portion_name or package_name}.py
de_tpl_project-0.2.3.dist-info/LICENSE.md
de_tpl_project-0.2.3.dist-info/METADATA
de_tpl_project-0.2.3.dist-info/WHEEL
de_tpl_project-0.2.3.dist-info/top_level.txt
de_tpl_project-0.2.3.dist-info/zip-safe
de_tpl_project-0.2.3.dist-info/RECORD
