Metadata-Version: 2.1
Name: de-tpl-project
Version: 0.2.3
Summary: de namespace module portion tpl_project: outsourced Python project files templates
Home-page: https://gitlab.com/degroup/de_tpl_project
Author: AndiEcker
Author-email: aecker2@gmail.com
License: OSI Approved :: GNU General Public License v3 or later (GPLv3+)
Keywords: configuration,development,environment,productivity
Platform: UNKNOWN
Classifier: Development Status :: 3 - Alpha
Classifier: License :: OSI Approved :: GNU General Public License v3 or later (GPLv3+)
Classifier: Natural Language :: English
Classifier: Operating System :: OS Independent
Classifier: Programming Language :: Python
Classifier: Programming Language :: Python :: 3
Classifier: Programming Language :: Python :: 3.6
Classifier: Topic :: Software Development :: Libraries :: Python Modules
Requires-Python: >=3.6
License-File: LICENSE.md
Provides-Extra: dev
Provides-Extra: docs
Provides-Extra: tests
